Workbook

Sheet Resumen
A1: RESUMEN DE CANTIDADES PRINCIPALES — MULTIFAMILIAR HERRERA
A2: Valores enlazados a las hojas de cálculo (se actualizan solos). Sin costos.
A4: Indicador | B4: Cantidad | C4: Und | D4: Nota
A5: Área cubierta P1–P5 | B5: ='Datos Revit'!H6 -> 566.81 | C5: m² | D5: Medida en Revit
A6: Área exterior (P1) | B6: ='Datos Revit'!H7 -> 37.09 | C6: m²
A7: Muros de mampostería (área neta, una cara) | B7: ='Datos Revit'!H9 -> 1359.15 | C7: m² | D7: 131 muros
A8: Pañete / estuco / pintura sobre muros (bruto, 2 caras) | B8: =Cantidades!J29 -> 2718.3 | C8: m² | D8: Descontar enchapes
A9: Puertas (todas) | B9: ='Datos Revit'!I25 -> 42 | C9: un | D9: Ver observación sobre KPI de 44
A10: Ventanas y ventanales | B10: ='Datos Revit'!I33 -> 38 | C10: un | D10: 32 convencionales + 6 paneles de muro cortina
A11: Aparatos sanitarios | B11: ='Datos Revit'!I43 -> 62 | C11: un | D11: Incluye mamparas
A12: Foso ascensor — concreto estructural (con desperdicio) | B12: ='Foso ascensor'!B29*(1+Supuestos!$B$7) -> 2.8539 | C12: m³ | D12: Losa + muros + columnas
A13: Foso ascensor — acero de refuerzo total (con desperdicio) | B13: =('Foso ascensor'!K53+'Foso ascensor'!K54)*(1+Supuestos!$B$6) -> 342.85986 | C13: kg | D13: #4 + #3
A14: Foso ascensor — excavación | B14: ='Foso ascensor'!B33 -> 12.1365 | C14: m³

Sheet Cantidades
A1: CUADRO DE CANTIDADES DE OBRA — MULTIFAMILIAR HERRERA (Puerto Berrío, Antioquia)
A2: Alcance: niveles P1–P5 terminados en el modelo Revit + foso de ascensor (plano EST-02). Sin precios: el presupuesto se maneja aparte. Fuente: R = medido en Revit · E = plano estructural EST-02 · D = derivada por fórmula (ver hoja Supuestos) · P = por confirmar.
A4: Ítem | B4: Descripción | C4: Especificación técnica | D4: Und | E4: P1 | F4: P2 | G4: P3 | H4: P4 | I4: P5 | J4: Cantidad total | K4: Fuente | L4: Observaciones
A5: 1 | B5: PRELIMINARES
A6: 1.1 | B6: Localización, trazado y replanteo | C6: Con equipo de topografía (estación total / nivel). Incluye referencias de ejes y niveles, mojones y estacas. | D6: m² | J6: ='Datos Revit'!H6+'Datos Revit'!H7 -> 603.9 | K6: R/D | L6: Área cubierta total P1–P5 + área exterior P1 (área de intervención por nivel).
A7: 1.2 | B7: Localización y replanteo del foso de ascensor | C7: Replanteo de ejes A-B / 1-2 según planta de geometría EST-02 (cotas a ejes: 1.10, 1.25, 1.19, 1.34 m). | D7: m² | J7: ='Foso ascensor'!$B$17*'Foso ascensor'!$B$18 -> 5.25 | K7: E | L7: Huella 2.10 × 2.50 m.
A8: 2 | B8: FOSO DE ASCENSOR — CIMENTACIÓN Y ESTRUCTURA (EST-02)
A9: 2.1 | B9: Excavación manual en material común | C9: Hasta cota N-1.55 (fondo de solado), con sobreancho de 0.30 m por lado. Incluye perfilado de fondo. Precaución: zapatas vecinas en ejes A y B (NSZ-2.00 / NIZ-2.50) — no descalzar. | D9: m³ | J9: ='Foso ascensor'!B33 -> 12.1365 | K9: E/D
A10: 2.2 | B10: Solado de limpieza e=0.05 m | C10: Concreto pobre f'c = 14 MPa (2.000 psi) bajo losa de fondo. | D10: m³ | J10: ='Foso ascensor'!B28*(1+Supuestos!$B$7) -> 0.252 | K10: D | L10: No dibujado en EST-02; recomendado. Incluye desperdicio.
A11: 2.3 | B11: Concreto losa de fondo e=0.20 m | C11: Concreto f'c = 21 MPa (3.000 psi) con aditivo impermeabilizante integral. Cara superior a N-1.30, inferior N-1.50. Recubrimiento 75 mm contra suelo. | D11: m³ | J11: ='Foso ascensor'!B26*(1+Supuestos!$B$7) -> 0.7791 | K11: E | L11: Incluye desperdicio. f'c NO indicado en EST-02: confirmar en notas generales (EST-01).
A12: 2.4 | B12: Concreto muros de contención e=0.15 m | C12: Concreto f'c = 21 MPa (3.000 psi) con aditivo impermeabilizante integral, h = 1.20 m sobre losa (hasta N-0.10). | D12: m³ | J12: ='Foso ascensor'!B27*(1+Supuestos!$B$7) -> 1.134 | K12: E | L12: Incluye desperdicio.
A13: 2.5 | B13: Concreto columnas 40×40 cm | C13: Concreto f'c = 21 MPa (3.000 psi). 4 und, de N-1.50 a N-0.10 (h = 1.40 m). Reciben perfil HE 200. | D13: m³ | J13: ='Foso ascensor'!B25*(1+Supuestos!$B$7) -> 0.9408 | K13: E | L13: Incluye desperdicio.
A14: 2.6 | B14: Acero de refuerzo #4 (1/2") | C14: Acero corrugado fy = 420 MPa (60.000 psi), NTC 2289. Losa doble parrilla #4 c/0.20; muros #4 c/0.20 en ambos sentidos; longitudinal de columnas 4 #4 por columna. Figurado según cartilla (hoja Foso ascensor). | D14: kg | J14: ='Foso ascensor'!K53*(1+Supuestos!$B$6) -> 273.24066 | K14: E/D | L14: Incluye desperdicio.
A15: 2.7 | B15: Acero de refuerzo #3 (3/8") — flejes | C15: Acero corrugado fy = 420 MPa, NTC 2289. Flejes cerrados #3 @0.075 m, L = 1.48 m, gancho a 135°. | D15: kg | J15: ='Foso ascensor'!K54*(1+Supuestos!$B$6) -> 69.6192 | K15: E/D | L15: Incluye desperdicio.
A16: 2.8 | B16: Formaleta para muros y columnas del foso | C16: Formaleta metálica o en madera cepillada, con desmoldante. Ambas caras de muros + caras exteriores de columnas. | D16: m² | J16: ='Foso ascensor'!B40 -> 22.72 | K16: D
A17: 2.9 | B17: Impermeabilización interior del foso | C17: Mortero impermeable cementicio (2 manos cruzadas) en fondo y muros + mediacaña en encuentros muro-losa. Rematar a N-0.10. | D17: m² | J17: ='Foso ascensor'!B41 -> 11.01 | K17: P | L17: No especificado en EST-02. Recomendado (foso bajo nivel de terreno).
A18: 2.10 | B18: Relleno compactado perimetral | C18: Material seleccionado de excavación o recebo, en capas ≤ 0.20 m compactadas al 95 % Proctor modificado. | D18: m³ | J18: ='Foso ascensor'!B35 -> 5.8065 | K18: D
A19: 2.11 | B19: Retiro de sobrantes | C19: Cargue, transporte y disposición en sitio autorizado (escombrera). | D19: m³ | J19: ='Foso ascensor'!B36 -> 8.229 | K19: D | L19: Volumen suelto (con expansión).
A20: 2.12 | B20: Platina base A36 300×300×16 mm | C20: Acero ASTM A36, 4 perforaciones para pernos Ø5/8". Nivelada con mortero sin retracción (grouting). | D20: un | J20: ='Foso ascensor'!B59 -> 4 | K20: E | L20: Peso total en hoja Foso ascensor.
A21: 2.13 | B21: Pernos de anclaje Ø5/8" con gancho | C21: Barra roscada ASTM F1554 Gr. 36 (o A307), embebido 314 mm, tuerca y arandela. 4 por platina. | D21: un | J21: ='Foso ascensor'!B61 -> 16 | K21: E
A22: 2.14 | B22: Soldadura de filete 5/16" | C22: Electrodo E70XX, todo el contorno del perfil HE 200 a la platina. | D22: ml | J22: ='Foso ascensor'!B62 -> 4.6 | K22: E/D | L22: Longitud aproximada por contorno de perfil.
A23: 2.15 | B23: Perfil HE 200 — columnas metálicas del ducto | C23: Perfil HE 200 (se asume HEB 200 = 61.3 kg/m), ASTM A572 Gr. 50 o A36, con anticorrosivo + esmalte. | D23: un | J23: ='Foso ascensor'!B63 -> 4 | K23: E/P | L23: Cantidad en ml PENDIENTE: depende de la altura total del ducto (no está en EST-02).
A24: 3 | B24: MAMPOSTERÍA
A25: 3.1 | B25: Muro en mampostería de arcilla | C25: Unidad de arcilla cocida NTC 4205 (tipo y espesor a confirmar), pega con mortero 1:4 tipo S (NTC 3329), juntas de 1 cm. Área neta medida en Revit (descuenta vanos, sin guardaescoba). | D25: m² | E25: ='Datos Revit'!C9 -> 339.4 | F25: ='Datos Revit'!D9 -> 251.1 | G25: ='Datos Revit'!E9 -> 256.42 | H25: ='Datos Revit'!F9 -> 256.08 | I25: ='Datos Revit'!G9 -> 256.15 | J25: =SUM(E25:I25) -> 1359.15 | K25: R | L25: 131 muros en P1–P5.
A26: 3.2 | B26: Unidades de mampostería (referencia) | C26: Bloque de arcilla 10×20×30 cm (supuesto). Incluye desperdicio. | D26: un | E26: =E25*Supuestos!$B$8*(1+Supuestos!$B$9) -> 5488.098 | F26: =F25*Supuestos!$B$8*(1+Supuestos!$B$9) -> 4060.287 | G26: =G25*Supuestos!$B$8*(1+Supuestos!$B$9) -> 4146.3114 | H26: =H25*Supuestos!$B$8*(1+Supuestos!$B$9) -> 4140.8136 | I26: =I25*Supuestos!$B$8*(1+Supuestos!$B$9) -> 4141.9455 | J26: =SUM(E26:I26) -> 21977.456 | K26: D | L26: Ajustar rendimiento en Supuestos según la unidad especificada.
A27: 3.3 | B27: Mortero de pega 1:4 | C27: Cemento gris + arena de pega, f'cm ≥ 12.5 MPa (tipo S). | D27: m³ | E27: =E25*Supuestos!$B$10 -> 4.0728 | F27: =F25*Supuestos!$B$10 -> 3.0132 | G27: =G25*Supuestos!$B$10 -> 3.07704 | H27: =H25*Supuestos!$B$10 -> 3.07296 | I27: =I25*Supuestos!$B$10 -> 3.0738 | J27: =SUM(E27:I27) -> 16.3098 | K27: D
A28: 4 | B28: PAÑETES Y ACABADOS DE MUROS
A29: 4.1 | B29: Pañete liso sobre muros (ambas caras) | C29: Mortero 1:4, e = 1.5 cm promedio, a plomo y regla. En fachada usar mortero 1:3 con impermeabilizante integral. | D29: m² | E29: =E25*Supuestos!$B$11 -> 678.8 | F29: =F25*Supuestos!$B$11 -> 502.2 | G29: =G25*Supuestos!$B$11 -> 512.84 | H29: =H25*Supuestos!$B$11 -> 512.16 | I29: =I25*Supuestos!$B$11 -> 512.3 | J29: =SUM(E29:I29) -> 2718.3 | K29: D | L29: Bruto: descontar las zonas que lleven enchape (baños, cocinas) cuando se definan.
A30: 4.2 | B30: Estuco + pintura vinilo tipo 1 (3 manos) | C30: Estuco plástico + vinilo tipo 1 NTC 1335, color a definir. Fachada: pintura para exteriores (elastomérica o acrílica). | D30: m² | E30: =E29 -> 678.8 | F30: =F29 -> 502.2 | G30: =G29 -> 512.84 | H30: =H29 -> 512.16 | I30: =I29 -> 512.3 | J30: =SUM(E30:I30) -> 2718.3 | K30: D | L30: Misma área bruta que el pañete; descontar enchapes.
A31: 4.3 | B31: Dinteles sobre vanos (puertas y ventanas) | C31: Dintel en concreto 21 MPa o en perfil, apoyo 0.20 m por lado. Ancho del muro. | D31: ml | E31: =SUMPRODUCT(('Datos Revit'!$B$13:$B$23+2*Supuestos!$B$20),'Datos Revit'!D$13:D$23)+SUMPRODUCT(('Datos Revit'!$B$29:$B$32+2*Supuestos!$B$20),'Datos Revit'!D$29:D$32) -> 18.075 | F31: =SUMPRODUCT(('Datos Revit'!$B$13:$B$23+2*Supuestos!$B$20),'Datos Revit'!E$13:E$23)+SUMPRODUCT(('Datos Revit'!$B$29:$B$32+2*Supuestos!$B$20),'Datos Revit'!E$29:E$32) -> 14.52 | G31: =SUMPRODUCT(('Datos Revit'!$B$13:$B$23+2*Supuestos!$B$20),'Datos Revit'!F$13:F$23)+SUMPRODUCT(('Datos Revit'!$B$29:$B$32+2*Supuestos!$B$20),'Datos Revit'!F$29:F$32) -> 21.41 | H31: =SUMPRODUCT(('Datos Revit'!$B$13:$B$23+2*Supuestos!$B$20),'Datos Revit'!G$13:G$23)+SUMPRODUCT(('Datos Revit'!$B$29:$B$32+2*Supuestos!$B$20),'Datos Revit'!G$29:G$32) -> 21.41 | I31: =SUMPRODUCT(('Datos Revit'!$B$13:$B$23+2*Supuestos!$B$20),'Datos Revit'!H$13:H$23)+SUMPRODUCT(('Datos Revit'!$B$29:$B$32+2*Supuestos!$B$20),'Datos Revit'!H$29:H$32) -> 21.41 | J31: =SUM(E31:I31) -> 96.825 | K31: D | L31: No incluye puertas de vestier Häfele (sin medida en el modelo).
A32: 5 | B32: PISOS
A33: 5.1 | B33: Alistado de piso (mortero de nivelación) | C33: Mortero 1:4, e = 4 cm, nivelado y afinado para recibir acabado. | D33: m² | E33: ='Datos Revit'!C6 -> 128.03 | F33: ='Datos Revit'!D6 -> 110.53 | G33: ='Datos Revit'!E6 -> 109.91 | H33: ='Datos Revit'!F6 -> 110.04 | I33: ='Datos Revit'!G6 -> 108.3 | J33: =SUM(E33:I33) -> 566.81 | K33: R | L33: Área cubierta por nivel (Revit).
A34: 5.2 | B34: Mortero para alistado | C34: Mortero 1:4. | D34: m³ | E34: =E33*Supuestos!$B$12 -> 5.1212 | F34: =F33*Supuestos!$B$12 -> 4.4212 | G34: =G33*Supuestos!$B$12 -> 4.3964 | H34: =H33*Supuestos!$B$12 -> 4.4016 | I34: =I33*Supuestos!$B$12 -> 4.332 | J34: =SUM(E34:I34) -> 22.6724 | K34: D
A35: 5.3 | B35: Acabado de piso interior | C35: Tipo POR DEFINIR (porcelanato / cerámica antideslizante en baños y balcones). Incluye pegante y boquilla. | D35: m² | E35: =E33 -> 128.03 | F35: =F33 -> 110.53 | G35: =G33 -> 109.91 | H35: =H33 -> 110.04 | I35: =I33 -> 108.3 | J35: =SUM(E35:I35) -> 566.81 | K35: R/P | L35: Área bruta; descontar muros si el área de Revit los incluye. Guardaescoba pendiente (perímetro de rooms).
A36: 5.4 | B36: Piso exterior / andén P1 | C36: Concreto 21 MPa e = 8 cm sobre recebo compactado, o adoquín. Acabado antideslizante. | D36: m² | E36: ='Datos Revit'!C7 -> 37.09 | F36: ='Datos Revit'!D7 -> 0 | G36: ='Datos Revit'!E7 -> 0 | H36: ='Datos Revit'!F7 -> 0 | I36: ='Datos Revit'!G7 -> 0 | J36: =SUM(E36:I36) -> 37.09 | K36: R
A37: 6 | B37: CIELORRASOS
A38: 6.1 | B38: Cielorraso interior | C38: Tipo POR DEFINIR: pañete bajo placa + estuco y vinilo, o drywall en placa de yeso 1/2". En baños usar placa RH. | D38: m² | E38: =E33 -> 128.03 | F38: =F33 -> 110.53 | G38: =G33 -> 109.91 | H38: =H33 -> 110.04 | I38: =I33 -> 108.3 | J38: =SUM(E38:I38) -> 566.81 | K38: D/P | L38: Aproximado = área cubierta por nivel. Confirmar con plano de cielos (RCP).
A39: 7 | B39: CARPINTERÍA — PUERTAS
A40: 7.1 | B40: Puerta de garaje — 2.4 × 2.1 m | C40: Puerta metálica enrollable o seccional, lámina cal. 20, con cerradura de seguridad. | D40: un | E40: ='Datos Revit'!D13 -> 1 | F40: ='Datos Revit'!E13 -> 0 | G40: ='Datos Revit'!F13 -> 0 | H40: ='Datos Revit'!G13 -> 0 | I40: ='Datos Revit'!H13 -> 0 | J40: =SUM(E40:I40) -> 1 | K40: R
A41: 7.2 | B41: Puerta principal de acceso — 0.9 × 2.1 m | C41: Puerta de seguridad metálica o en madera maciza, marco metálico cal. 18, cerradura de seguridad y mirilla. | D41: un | E41: ='Datos Revit'!D14 -> 1 | F41: ='Datos Revit'!E14 -> 0 | G41: ='Datos Revit'!F14 -> 0 | H41: ='Datos Revit'!G14 -> 0 | I41: ='Datos Revit'!H14 -> 0 | J41: =SUM(E41:I41) -> 1 | K41: R
A42: 7.3 | B42: Puerta de acceso secundario — 0.915 × 2.13 m | C42: Puerta de seguridad metálica o en madera maciza, marco metálico cal. 18, cerradura de seguridad y mirilla. | D42: un | E42: ='Datos Revit'!D15 -> 1 | F42: ='Datos Revit'!E15 -> 0 | G42: ='Datos Revit'!F15 -> 0 | H42: ='Datos Revit'!G15 -> 0 | I42: ='Datos Revit'!H15 -> 0 | J42: =SUM(E42:I42) -> 1 | K42: R
A43: 7.4 | B43: Puerta corrediza social (balcón) — 1.2 × 2.1 m | C43: Puerta corrediza en aluminio con vidrio de seguridad templado 6 mm (NSR-10 Título K). | D43: un | E43: ='Datos Revit'!D16 -> 1 | F43: ='Datos Revit'!E16 -> 0 | G43: ='Datos Revit'!F16 -> 0 | H43: ='Datos Revit'!G16 -> 0 | I43: ='Datos Revit'!H16 -> 0 | J43: =SUM(E43:I43) -> 1 | K43: R
A44: 7.5 | B44: Puerta corrediza de habitación/closet — 0.9 × 2.1 m | C44: Hoja corrediza entamborada en MDF, herraje de riel superior, manija embutida. | D44: un | E44: ='Datos Revit'!D17 -> 3 | F44: ='Datos Revit'!E17 -> 0 | G44: ='Datos Revit'!F17 -> 0 | H44: ='Datos Revit'!G17 -> 0 | I44: ='Datos Revit'!H17 -> 0 | J44: =SUM(E44:I44) -> 3 | K44: R
A45: 7.6 | B45: Puerta corrediza de baño/closet menor — 0.7 × 2.1 m | C45: Hoja corrediza entamborada en MDF, herraje de riel superior, manija embutida. | D45: un | E45: ='Datos Revit'!D18 -> 0 | F45: ='Datos Revit'!E18 -> 3 | G45: ='Datos Revit'!F18 -> 2 | H45: ='Datos Revit'!G18 -> 2 | I45: ='Datos Revit'!H18 -> 2 | J45: =SUM(E45:I45) -> 9 | K45: R
A46: 7.7 | B46: Puerta batiente de habitación — 0.8 × 2.1 m | C46: Hoja entamborada en MDF, marco en madera, bisagras de 3½" y cerradura de pomo. | D46: un | E46: ='Datos Revit'!D19 -> 2 | F46: ='Datos Revit'!E19 -> 1 | G46: ='Datos Revit'!F19 -> 0 | H46: ='Datos Revit'!G19 -> 0 | I46: ='Datos Revit'!H19 -> 0 | J46: =SUM(E46:I46) -> 3 | K46: R
A47: 7.8 | B47: Puerta batiente de habitación — 0.9 × 2.1 m | C47: Hoja entamborada en MDF, marco en madera, bisagras de 3½" y cerradura de pomo. | D47: un | E47: ='Datos Revit'!D20 -> 2 | F47: ='Datos Revit'!E20 -> 0 | G47: ='Datos Revit'!F20 -> 3 | H47: ='Datos Revit'!G20 -> 3 | I47: ='Datos Revit'!H20 -> 3 | J47: =SUM(E47:I47) -> 11 | K47: R
A48: 7.9 | B48: Puerta batiente de baño/closet — 0.7 × 2.1 m | C48: Hoja entamborada en MDF RH (resistente a humedad), marco en madera, cerradura de baño. | D48: un | E48: ='Datos Revit'!D21 -> 0 | F48: ='Datos Revit'!E21 -> 1 | G48: ='Datos Revit'!F21 -> 1 | H48: ='Datos Revit'!G21 -> 1 | I48: ='Datos Revit'!H21 -> 1 | J48: =SUM(E48:I48) -> 4 | K48: R
A49: 7.10 | B49: Puerta principal de apartamento — 1 × 2.1 m | C49: Puerta de seguridad metálica o en madera maciza, marco metálico cal. 18, cerradura de seguridad y mirilla. | D49: un | E49: ='Datos Revit'!D22 -> 0 | F49: ='Datos Revit'!E22 -> 1 | G49: ='Datos Revit'!F22 -> 0 | H49: ='Datos Revit'!G22 -> 0 | I49: ='Datos Revit'!H22 -> 0 | J49: =SUM(E49:I49) -> 1 | K49: R
A50: 7.11 | B50: Puerta-ventanal corrediza (balcón) — 1.6 × 2.3 m | C50: Puerta corrediza en aluminio con vidrio de seguridad templado 6 mm (NSR-10 Título K). | D50: un | E50: ='Datos Revit'!D23 -> 0 | F50: ='Datos Revit'!E23 -> 0 | G50: ='Datos Revit'!F23 -> 1 | H50: ='Datos Revit'!G23 -> 1 | I50: ='Datos Revit'!H23 -> 1 | J50: =SUM(E50:I50) -> 3 | K50: R
A51: 7.12 | B51: Puerta corrediza de vestier (herraje Häfele) — ≈7.73 m² de hoja (total Revit) | C51: Puertas corredizas de vestier con herraje Häfele, hoja en MDF/aglomerado enchapado. | D51: un | E51: ='Datos Revit'!D24 -> 0 | F51: ='Datos Revit'!E24 -> 1 | G51: ='Datos Revit'!F24 -> 1 | H51: ='Datos Revit'!G24 -> 1 | I51: ='Datos Revit'!H24 -> 1 | J51: =SUM(E51:I51) -> 4 | K51: R
A52: 8 | B52: VENTANERÍA Y VIDRIOS
A53: 8.1 | B53: Ventana de habitación — 0.8 × 0.8 m | C53: Ventana en aluminio (proyectante o corrediza), vidrio incoloro 4 mm, empaques y sellos. | D53: un | E53: ='Datos Revit'!D29 -> 0 | F53: ='Datos Revit'!E29 -> 3 | G53: ='Datos Revit'!F29 -> 8 | H53: ='Datos Revit'!G29 -> 8 | I53: ='Datos Revit'!H29 -> 8 | J53: =SUM(E53:I53) -> 27 | K53: R
A54: 8.2 | B54: Ventana de baño/cocina — 0.91 × 0.91 m | C54: Ventana en aluminio, vidrio esmerilado/sandblasting 4 mm (privacidad), con celosía de ventilación. | D54: un | E54: ='Datos Revit'!D30 -> 0 | F54: ='Datos Revit'!E30 -> 2 | G54: ='Datos Revit'!F30 -> 1 | H54: ='Datos Revit'!G30 -> 1 | I54: ='Datos Revit'!H30 -> 1 | J54: =SUM(E54:I54) -> 5 | K54: R
A55: 8.3 | B55: Ventanal de circulación (hall/escalera) — 0.9 × 2.41 m | C55: Perfilería en aluminio, vidrio de seguridad laminado o templado 6 mm (vano a piso, NSR-10 Título K). | D55: un | E55: ='Datos Revit'!D31 -> 0 | F55: ='Datos Revit'!E31 -> 1 | G55: ='Datos Revit'!F31 -> 1 | H55: ='Datos Revit'!G31 -> 1 | I55: ='Datos Revit'!H31 -> 1 | J55: =SUM(E55:I55) -> 4 | K55: R
A56: 8.4 | B56: Ventanal de fachada — acceso — 0.68 × 2.2 m | C56: Perfilería en aluminio, vidrio de seguridad laminado o templado 6 mm (vano a piso, NSR-10 Título K). | D56: un | E56: ='Datos Revit'!D32 -> 2 | F56: ='Datos Revit'!E32 -> 0 | G56: ='Datos Revit'!F32 -> 0 | H56: ='Datos Revit'!G32 -> 0 | I56: ='Datos Revit'!H32 -> 0 | J56: =SUM(E56:I56) -> 2 | K56: R
A57: 8.5 | B57: Área de vidrio en ventanas y ventanales | C57: Suma de ancho × alto × cantidad. | D57: m² | E57: =SUMPRODUCT('Datos Revit'!$B$29:$B$32,'Datos Revit'!$C$29:$C$32,'Datos Revit'!D$29:D$32) -> 2.992 | F57: =SUMPRODUCT('Datos Revit'!$B$29:$B$32,'Datos Revit'!$C$29:$C$32,'Datos Revit'!E$29:E$32) -> 5.7452 | G57: =SUMPRODUCT('Datos Revit'!$B$29:$B$32,'Datos Revit'!$C$29:$C$32,'Datos Revit'!F$29:F$32) -> 8.1171 | H57: =SUMPRODUCT('Datos Revit'!$B$29:$B$32,'Datos Revit'!$C$29:$C$32,'Datos Revit'!G$29:G$32) -> 8.1171 | I57: =SUMPRODUCT('Datos Revit'!$B$29:$B$32,'Datos Revit'!$C$29:$C$32,'Datos Revit'!H$29:H$32) -> 8.1171 | J57: =SUM(E57:I57) -> 33.0885 | K57: D | L57: No incluye vidrio de puertas-ventanal (ver ítem siguiente).
A58: 8.6 | B58: Área de vidrio de seguridad en puertas-ventanal y puerta de balcón | C58: Vidrio templado 6 mm. | D58: m² | E58: ='Datos Revit'!$B$23*'Datos Revit'!$C$23*'Datos Revit'!D23+'Datos Revit'!$B$16*'Datos Revit'!$C$16*'Datos Revit'!D16 -> 2.52 | F58: ='Datos Revit'!$B$23*'Datos Revit'!$C$23*'Datos Revit'!E23+'Datos Revit'!$B$16*'Datos Revit'!$C$16*'Datos Revit'!E16 -> 0 | G58: ='Datos Revit'!$B$23*'Datos Revit'!$C$23*'Datos Revit'!F23+'Datos Revit'!$B$16*'Datos Revit'!$C$16*'Datos Revit'!F16 -> 3.68 | H58: ='Datos Revit'!$B$23*'Datos Revit'!$C$23*'Datos Revit'!G23+'Datos Revit'!$B$16*'Datos Revit'!$C$16*'Datos Revit'!G16 -> 3.68 | I58: ='Datos Revit'!$B$23*'Datos Revit'!$C$23*'Datos Revit'!H23+'Datos Revit'!$B$16*'Datos Revit'!$C$16*'Datos Revit'!H16 -> 3.68 | J58: =SUM(E58:I58) -> 13.56 | K58: D
A59: 8.7 | B59: Alfajías en ventanas (excepto vanos a piso) | C59: Alfajía prefabricada en concreto o granito, con gotero, pendiente hacia el exterior. | D59: ml | E59: =SUMPRODUCT('Datos Revit'!$B$29:$B$30,'Datos Revit'!D$29:D$30) -> 0 | F59: =SUMPRODUCT('Datos Revit'!$B$29:$B$30,'Datos Revit'!E$29:E$30) -> 4.22 | G59: =SUMPRODUCT('Datos Revit'!$B$29:$B$30,'Datos Revit'!F$29:F$30) -> 7.31 | H59: =SUMPRODUCT('Datos Revit'!$B$29:$B$30,'Datos Revit'!G$29:G$30) -> 7.31 | I59: =SUMPRODUCT('Datos Revit'!$B$29:$B$30,'Datos Revit'!H$29:H$30) -> 7.31 | J59: =SUM(E59:I59) -> 26.15 | K59: D | L59: Solo ventanas de habitación y baño/cocina.
A60: 9 | B60: APARATOS SANITARIOS, GRIFERÍAS E INCRUSTACIONES
A61: 9.1 | B61: Sanitario | C61: Sanitario de porcelana vitrificada, tanque de bajo consumo (≤ 4.8 L/descarga, NTC 920), con grifería de llenado y asiento. | D61: un | E61: ='Datos Revit'!D37 -> 2 | F61: ='Datos Revit'!E37 -> 3 | G61: ='Datos Revit'!F37 -> 3 | H61: ='Datos Revit'!G37 -> 3 | I61: ='Datos Revit'!H37 -> 3 | J61: =SUM(E61:I61) -> 14 | K61: R
A62: 9.2 | B62: Cabina de ducha | C62: Zona de ducha con piso en cerámica antideslizante, pendiente 1–2 % al sifón; cabina según modelo Revit. | D62: un | E62: ='Datos Revit'!D38 -> 0 | F62: ='Datos Revit'!E38 -> 3 | G62: ='Datos Revit'!F38 -> 3 | H62: ='Datos Revit'!G38 -> 3 | I62: ='Datos Revit'!H38 -> 3 | J62: =SUM(E62:I62) -> 12 | K62: R
A63: 9.3 | B63: Regadera de ducha | C63: Regadera + mezclador monocontrol cromado (agua fría/caliente), sistema ahorrador. | D63: un | E63: ='Datos Revit'!D39 -> 0 | F63: ='Datos Revit'!E39 -> 3 | G63: ='Datos Revit'!F39 -> 3 | H63: ='Datos Revit'!G39 -> 3 | I63: ='Datos Revit'!H39 -> 3 | J63: =SUM(E63:I63) -> 12 | K63: R
A64: 9.4 | B64: Ducha accesible (con barras) | C64: Ducha a nivel sin sardinel, asiento abatible y barras de apoyo en acero inoxidable (NTC 6047 accesibilidad). | D64: un | E64: ='Datos Revit'!D40 -> 1 | F64: ='Datos Revit'!E40 -> 0 | G64: ='Datos Revit'!F40 -> 0 | H64: ='Datos Revit'!G40 -> 0 | I64: ='Datos Revit'!H40 -> 0 | J64: =SUM(E64:I64) -> 1 | K64: R
A65: 9.5 | B65: Lavamanos de baño | C65: Lavamanos de porcelana (de incrustar u ovalín), con sifón, desagüe y grifería monocontrol ahorradora. | D65: un | E65: ='Datos Revit'!D41 -> 2 | F65: ='Datos Revit'!E41 -> 3 | G65: ='Datos Revit'!F41 -> 3 | H65: ='Datos Revit'!G41 -> 3 | I65: ='Datos Revit'!H41 -> 3 | J65: =SUM(E65:I65) -> 14 | K65: R
A66: 9.6 | B66: Mampara de baño | C66: Mampara en vidrio templado 8 mm con perfilería en aluminio (NSR-10 Título K). | D66: un | E66: ='Datos Revit'!D42 -> 0 | F66: ='Datos Revit'!E42 -> 0 | G66: ='Datos Revit'!F42 -> 3 | H66: ='Datos Revit'!G42 -> 3 | I66: ='Datos Revit'!H42 -> 3 | J66: =SUM(E66:I66) -> 9 | K66: R
A67: 9.7 | B67: Grifería de lavamanos | C67: Monocontrol cromada, aireador ahorrador. | D67: un | E67: ='Datos Revit'!D41 -> 2 | F67: ='Datos Revit'!E41 -> 3 | G67: ='Datos Revit'!F41 -> 3 | H67: ='Datos Revit'!G41 -> 3 | I67: ='Datos Revit'!H41 -> 3 | J67: =SUM(E67:I67) -> 14 | K67: D | L67: 1 por lavamanos.
A68: 9.8 | B68: Mezclador de ducha | C68: Monocontrol empotrado, cartucho cerámico. | D68: un | E68: ='Datos Revit'!D39+'Datos Revit'!D40 -> 1 | F68: ='Datos Revit'!E39+'Datos Revit'!E40 -> 3 | G68: ='Datos Revit'!F39+'Datos Revit'!F40 -> 3 | H68: ='Datos Revit'!G39+'Datos Revit'!G40 -> 3 | I68: ='Datos Revit'!H39+'Datos Revit'!H40 -> 3 | J68: =SUM(E68:I68) -> 13 | K68: D | L68: Regaderas + ducha accesible.
A69: 9.9 | B69: Juego de incrustaciones por baño | C69: Toallero, jabonera, portarrollos y gancho, en porcelana o acero inoxidable. | D69: jg | E69: ='Datos Revit'!D37 -> 2 | F69: ='Datos Revit'!E37 -> 3 | G69: ='Datos Revit'!F37 -> 3 | H69: ='Datos Revit'!G37 -> 3 | I69: ='Datos Revit'!H37 -> 3 | J69: =SUM(E69:I69) -> 14 | K69: D | L69: 1 juego por baño (= N° de sanitarios).
A70: 9.10 | B70: Sifón de piso 3" con rejilla | C70: PVC sanitario + rejilla en acero inoxidable. | D70: un | E70: ='Datos Revit'!D38+'Datos Revit'!D40 -> 1 | F70: ='Datos Revit'!E38+'Datos Revit'!E40 -> 3 | G70: ='Datos Revit'!F38+'Datos Revit'!F40 -> 3 | H70: ='Datos Revit'!G38+'Datos Revit'!G40 -> 3 | I70: ='Datos Revit'!H38+'Datos Revit'!H40 -> 3 | J70: =SUM(E70:I70) -> 13 | K70: D | L70: Mínimo 1 por ducha; agregar los de cocina/zona de ropas.
A71: 10 | B71: EQUIPO DE ASCENSOR
A72: 10.1 | B72: Ascensor de pasajeros | C72: Ascensor eléctrico sin cuarto de máquinas (MRL), capacidad y paradas POR DEFINIR (6 niveles), NTC 5926 / EN 81-20. Incluye cabina, puertas de piso, guías, contrapeso y control. | D72: gl | J72: 1 | K72: P | L72: QA crítico: el ascensor no está modelado en Revit. El foso de EST-02 tiene luz libre 1.50 × 1.90 m: validar con el proveedor.

Sheet Supuestos
A1: SUPUESTOS Y PARÁMETROS DE CÁLCULO
A2: Celdas en azul con fondo amarillo = parámetros editables. Al cambiarlos se recalculan todas las cantidades derivadas. Fuente indicada en la columna D.
A3: Parámetro | B3: Valor | C3: Und | D3: Fuente / criterio
A4: Peso nominal barra #3 (3/8") | B4: 0.56 | C4: kg/m | D4: NSR-10 / NTC 2289
A5: Peso nominal barra #4 (1/2") | B5: 0.994 | C5: kg/m | D5: NSR-10 / NTC 2289
A6: Desperdicio acero de refuerzo | B6: 0.05 | D6: Criterio usual de obra (traslapos y cortes)
A7: Desperdicio concreto | B7: 0.05 | D7: Criterio usual de obra
A8: Unidades de mampostería por m² (bloque arcilla 10×20×30 cm, junta 1 cm) | B8: 15.4 | C8: un/m² | D8: 1/(0.31×0.21). AJUSTAR si la unidad especificada es otra (p.ej. tolete 6×12×24 ≈ 54 un/m² en soga)
A9: Desperdicio unidades de mampostería | B9: 0.05 | D9: Criterio usual de obra
A10: Mortero de pega por m² de muro (bloque e=10 cm) | B10: 0.012 | C10: m³/m² | D10: Rendimiento de referencia; ajustar según unidad y espesor de junta
A11: Caras de pañete/estuco/pintura por muro | B11: 2 | C11: caras | D11: Supuesto: todos los muros se revocan por ambas caras (bruto, sin descontar enchapes)
A12: Espesor de alistado (mortero de nivelación) de piso | B12: 0.04 | C12: m | D12: Supuesto de diseño; confirmar con nivel de acabado
A13: Sobreancho de excavación por lado (foso) | B13: 0.3 | C13: m | D13: Espacio de trabajo para formaleta exterior
A14: Profundidad de excavación foso (desde N-0.10) | B14: 1.45 | C14: m | D14: N-0.10 a N-1.50 (EST-02) + 0.05 de solado
A15: Factor de expansión del suelo (sobrantes) | B15: 1.3 | D15: Criterio usual para material común
A16: Espesor solado de limpieza | B16: 0.05 | C16: m | D16: Recomendado bajo losa en contacto con suelo (no dibujado en EST-02)
A17: Sobreancho solado por lado | B17: 0.1 | C17: m | D17: Criterio usual
A18: Densidad acero estructural | B18: 7850 | C18: kg/m³ | D18: Valor estándar
A19: Peso perfil HE 200 (se asume HEB 200) | B19: 61.3 | C19: kg/m | D19: HEB 200 = 61.3 kg/m; si es HEA 200 usar 42.3 kg/m. EST-02 no lo precisa
A20: Apoyo de dintel por lado | B20: 0.2 | C20: m | D20: Criterio usual en mampostería
A21: Recubrimiento de impermeabilización interior foso | B21: 1 | D21: 1 = incluir (recomendado para foso bajo nivel de piso)

Sheet Datos Revit
A1: DATOS DE ENTRADA — EXTRAÍDOS DEL MODELO REVIT (MULTIF H - RVT.rvt)
A2: Fuente: dashboard index.html (consulta directa al modelo). Solo niveles P1–P5 terminados; P6/P7 y cubierta en diseño, NO incluidos.
A4: 1. SUPERFICIES Y MUROS POR NIVEL
A5: Concepto | B5: Und | C5: P1 | D5: P2 | E5: P3 | F5: P4 | G5: P5 | H5: Total | J5: Nota
A6: Área cubierta | B6: m² | C6: 128.03 | D6: 110.53 | E6: 109.91 | F6: 110.04 | G6: 108.3 | H6: =SUM(C6:G6) -> 566.81 | J6: Programa de superficies Revit
A7: Área exterior | B7: m² | C7: 37.09 | D7: 0 | E7: 0 | F7: 0 | G7: 0 | H7: =SUM(C7:G7) -> 37.09 | J7: Solo P1
A8: N° de muros de mampostería | B8: un | C8: 24 | D8: 29 | E8: 26 | F8: 26 | G8: 26 | H8: =SUM(C8:G8) -> 131
A9: Área de muros de mampostería (neta, una cara) | B9: m² | C9: 339.4 | D9: 251.1 | E9: 256.42 | F9: 256.08 | G9: 256.15 | H9: =SUM(C9:G9) -> 1359.15 | J9: Revit descuenta vanos de puertas/ventanas. Sin guardaescoba
A11: 2. PUERTAS — por función y medida
A12: Función | B12: Ancho (m) | C12: Alto (m) | D12: P1 | E12: P2 | F12: P3 | G12: P4 | H12: P5 | I12: Total | J12: Nota
A13: Puerta de garaje | B13: 2.4 | C13: 2.1 | D13: 1 | E13: 0 | F13: 0 | G13: 0 | H13: 0 | I13: =SUM(D13:H13) -> 1
A14: Puerta principal de acceso | B14: 0.9 | C14: 2.1 | D14: 1 | E14: 0 | F14: 0 | G14: 0 | H14: 0 | I14: =SUM(D14:H14) -> 1
A15: Puerta de acceso secundario | B15: 0.915 | C15: 2.134 | D15: 1 | E15: 0 | F15: 0 | G15: 0 | H15: 0 | I15: =SUM(D15:H15) -> 1 | J15: Medida imperial 3'×7'
A16: Puerta corrediza social (balcón) | B16: 1.2 | C16: 2.1 | D16: 1 | E16: 0 | F16: 0 | G16: 0 | H16: 0 | I16: =SUM(D16:H16) -> 1
A17: Puerta corrediza de habitación/closet | B17: 0.9 | C17: 2.1 | D17: 3 | E17: 0 | F17: 0 | G17: 0 | H17: 0 | I17: =SUM(D17:H17) -> 3
A18: Puerta corrediza de baño/closet menor | B18: 0.7 | C18: 2.1 | D18: 0 | E18: 3 | F18: 2 | G18: 2 | H18: 2 | I18: =SUM(D18:H18) -> 9
A19: Puerta batiente de habitación | B19: 0.8 | C19: 2.1 | D19: 2 | E19: 1 | F19: 0 | G19: 0 | H19: 0 | I19: =SUM(D19:H19) -> 3
A20: Puerta batiente de habitación | B20: 0.9 | C20: 2.1 | D20: 2 | E20: 0 | F20: 3 | G20: 3 | H20: 3 | I20: =SUM(D20:H20) -> 11
A21: Puerta batiente de baño/closet | B21: 0.7 | C21: 2.1 | D21: 0 | E21: 1 | F21: 1 | G21: 1 | H21: 1 | I21: =SUM(D21:H21) -> 4
A22: Puerta principal de apartamento | B22: 1 | C22: 2.1 | D22: 0 | E22: 1 | F22: 0 | G22: 0 | H22: 0 | I22: =SUM(D22:H22) -> 1
A23: Puerta-ventanal corrediza (balcón) | B23: 1.6 | C23: 2.3 | D23: 0 | E23: 0 | F23: 1 | G23: 1 | H23: 1 | I23: =SUM(D23:H23) -> 3
A24: Puerta corrediza de vestier (herraje Häfele) | D24: 0 | E24: 1 | F24: 1 | G24: 1 | H24: 1 | I24: =SUM(D24:H24) -> 4 | J24: Revit reporta ≈7.73 m² de hoja; sin ancho/alto definido
A25: TOTAL PUERTAS | D25: =SUM(D13:D24) -> 11 | E25: =SUM(E13:E24) -> 7 | F25: =SUM(F13:F24) -> 8 | G25: =SUM(G13:G24) -> 8 | H25: =SUM(H13:H24) -> 8 | I25: =SUM(I13:I24) -> 42
A27: 3. VENTANAS Y VENTANALES — por función y medida
A28: Función | B28: Ancho (m) | C28: Alto (m) | D28: P1 | E28: P2 | F28: P3 | G28: P4 | H28: P5 | I28: Total | J28: Nota
A29: Ventana de habitación | B29: 0.8 | C29: 0.8 | D29: 0 | E29: 3 | F29: 8 | G29: 8 | H29: 8 | I29: =SUM(D29:H29) -> 27
A30: Ventana de baño/cocina | B30: 0.91 | C30: 0.91 | D30: 0 | E30: 2 | F30: 1 | G30: 1 | H30: 1 | I30: =SUM(D30:H30) -> 5
A31: Ventanal de circulación (hall/escalera) | B31: 0.9 | C31: 2.41 | D31: 0 | E31: 1 | F31: 1 | G31: 1 | H31: 1 | I31: =SUM(D31:H31) -> 4 | J31: Panel de muro cortina
A32: Ventanal de fachada — acceso | B32: 0.68 | C32: 2.2 | D32: 2 | E32: 0 | F32: 0 | G32: 0 | H32: 0 | I32: =SUM(D32:H32) -> 2 | J32: Panel de muro cortina
A33: TOTAL VENTANAS | D33: =SUM(D29:D32) -> 2 | E33: =SUM(E29:E32) -> 6 | F33: =SUM(F29:F32) -> 10 | G33: =SUM(G29:G32) -> 10 | H33: =SUM(H29:H32) -> 10 | I33: =SUM(I29:I32) -> 38
A35: 4. APARATOS SANITARIOS — verificados elemento por elemento
A36: Aparato | D36: P1 | E36: P2 | F36: P3 | G36: P4 | H36: P5 | I36: Total | J36: Nota
A37: Sanitario | D37: 2 | E37: 3 | F37: 3 | G37: 3 | H37: 3 | I37: =SUM(D37:H37) -> 14
A38: Cabina de ducha | D38: 0 | E38: 3 | F38: 3 | G38: 3 | H38: 3 | I38: =SUM(D38:H38) -> 12
A39: Regadera de ducha | D39: 0 | E39: 3 | F39: 3 | G39: 3 | H39: 3 | I39: =SUM(D39:H39) -> 12
A40: Ducha accesible (con barras) | D40: 1 | E40: 0 | F40: 0 | G40: 0 | H40: 0 | I40: =SUM(D40:H40) -> 1
A41: Lavamanos de baño | D41: 2 | E41: 3 | F41: 3 | G41: 3 | H41: 3 | I41: =SUM(D41:H41) -> 14
A42: Mampara de baño | D42: 0 | E42: 0 | F42: 3 | G42: 3 | H42: 3 | I42: =SUM(D42:H42) -> 9
A43: TOTAL APARATOS | D43: =SUM(D37:D42) -> 5 | E43: =SUM(E37:E42) -> 12 | F43: =SUM(F37:F42) -> 15 | G43: =SUM(G37:G42) -> 15 | H43: =SUM(H37:H42) -> 15 | I43: =SUM(I37:I42) -> 62

Sheet Foso ascensor
A1: MEMORIA DE CÁLCULO — FOSO DE ASCENSOR (plano EST-02, versión 01, 19/06/2026)
A2: Diseño estructural: A3 Ingeniería. Escala 1:25. Cotas en m. Valores en azul tomados del plano; las cantidades son fórmulas.
A4: A. GEOMETRÍA (según planta, cortes A-A y B-B)
A5: Dato | B5: Valor | C5: Und | D5: Fuente
A6: Luz libre interior del foso — sentido X | B6: 1.5 | C6: m | D6: Planta foso
A7: Luz libre interior del foso — sentido Y | B7: 1.9 | C7: m | D7: Planta foso
A8: Espesor muros de concreto | B8: 0.15 | C8: m | D8: Planta foso: Muro e=0.15m
A9: Lado columna cuadrada (4 und, en esquinas) | B9: 0.4 | C9: m | D9: Columna 40×40
A10: Número de columnas | B10: 4 | C10: un | D10: Planta foso
A11: Distancia libre entre caras de columnas — X | B11: 1.3 | C11: m | D11: Planta foso
A12: Distancia libre entre caras de columnas — Y | B12: 1.7 | C12: m | D12: Planta foso
A13: Altura total foso (N-0.10 a N-1.50) | B13: 1.4 | C13: m | D13: Cortes A-A / B-B
A14: Espesor losa de fondo | B14: 0.2 | C14: m | D14: Losa e=0.20m
A15: Losa — dimensión exterior X (luz + 2 muros) | B15: =$B$6+2*$B$8 -> 1.8 | C15: m
A16: Losa — dimensión exterior Y (luz + 2 muros) | B16: =$B$7+2*$B$8 -> 2.2 | C16: m
A17: Huella total con columnas — X | B17: =$B$11+2*$B$9 -> 2.1 | C17: m
A18: Huella total con columnas — Y | B18: =$B$12+2*$B$9 -> 2.5 | C18: m
A19: Traslapo columna–losa por esquina (lado) | B19: =$B$9-($B$17-$B$15)/2 -> 0.25 | C19: m
A20: Altura libre muros (sobre losa) | B20: =$B$13-$B$14 -> 1.2 | C20: m
A21: Profundidad útil del foso (N-0.10 a cara superior losa) | B21: =$B$20 -> 1.2 | C21: m | D21: Verificar contra la ficha técnica del ascensor elegido
A23: B. CONCRETO
A24: Elemento | B24: Cant. | C24: Und | D24: Cálculo
A25: Columnas 40×40 (altura total foso) | B25: =$B$10*$B$9^2*$B$13 -> 0.896 | C25: m³ | D25: 4 × 0.40 × 0.40 × 1.40
A26: Losa de fondo e=0.20 (descontando columnas) | B26: =$B$15*$B$16*$B$14-$B$10*$B$19^2*$B$14 -> 0.742 | C26: m³ | D26: 1.80 × 2.20 × 0.20 − 4 × 0.25² × 0.20
A27: Muros e=0.15 (entre columnas, sobre losa) | B27: =(2*$B$11+2*$B$12)*$B$20*$B$8 -> 1.08 | C27: m³ | D27: (2×1.30 + 2×1.70) × 1.20 × 0.15
A28: Solado de limpieza (concreto pobre) | B28: =($B$15+2*Supuestos!$B$17)*($B$16+2*Supuestos!$B$17)*Supuestos!$B$16 -> 0.24 | C28: m³ | D28: (1.80+0.20) × (2.20+0.20) × 0.05 — recomendado
A29: TOTAL CONCRETO ESTRUCTURAL (sin desperdicio) | B29: =B25+B26+B27 -> 2.718 | C29: m³
A31: C. MOVIMIENTO DE TIERRA Y FORMALETA
A32: Concepto | B32: Cant. | C32: Und | D32: Cálculo
A33: Excavación manual | B33: =($B$17+2*Supuestos!$B$13)*($B$18+2*Supuestos!$B$13)*Supuestos!$B$14 -> 12.1365 | C33: m³ | D33: (2.10+0.60) × (2.50+0.60) × 1.45
A34: Volumen ocupado por el foso + solado | B34: =($B$15*$B$16+$B$10*($B$9^2-$B$19^2))*$B$13+B28 -> 6.33 | C34: m³ | D34: Huella real (losa + salientes de columnas) × 1.40 + solado
A35: Relleno compactado perimetral (material seleccionado) | B35: =B33-B34 -> 5.8065 | C35: m³ | D35: Excavación − volumen ocupado. Compactar en capas ≤ 0.20 m
A36: Retiro de sobrantes (suelto) | B36: =(B33-B35)*Supuestos!$B$15 -> 8.229 | C36: m³ | D36: (Excavación − relleno) × factor de expansión
A37: Formaleta muros — cara interior | B37: =2*($B$6+$B$7)*$B$20 -> 8.16 | C37: m² | D37: Perímetro interior 6.80 × 1.20
A38: Formaleta muros — cara exterior | B38: =(2*$B$11+2*$B$12)*$B$13 -> 8.4 | C38: m² | D38: Tramos entre columnas 6.00 × 1.40
A39: Formaleta columnas — caras exteriores expuestas | B39: =$B$10*(2*$B$9+2*($B$9-$B$19))*$B$13 -> 6.16 | C39: m² | D39: 4 × (2×0.40 + 2×0.15) × 1.40
A40: TOTAL FORMALETA | B40: =SUM(B37:B39) -> 22.72 | C40: m²
A41: Impermeabilización interior (fondo + muros) | B41: =($B$6*$B$7+2*($B$6+$B$7)*$B$20)*Supuestos!$B$21 -> 11.01 | C41: m² | D41: 1.50×1.90 + 6.80×1.20 — no especificado en EST-02, recomendado
A43: D. CARTILLA DE DESPIECE — ACERO DE REFUERZO fy = 420 MPa
A44: Elemento / posición | B44: Barra | C44: Separación (m) | D44: Long. a distribuir (m) | E44: N° barras por capa/elem. | F44: Capas o elementos | G44: N° barras total | H44: L barra (m) | I44: Long. total (m) | J44: kg/m | K44: Peso (kg) | L44: Fuente en plano
A45: Losa fondo — barras sentido X (corto) | B45: #4 | C45: 0.2 | D45: 2.08 | E45: =ROUNDUP(D45/C45,0)+1 -> 12 | F45: 2 | G45: =E45*F45 -> 24 | H45: 2.2 | I45: =G45*H45 -> 52.8 | J45: =Supuestos!$B$5 -> 0.994 | K45: =I45*J45 -> 52.4832 | L45: Corte A-A: #4 c/0.20 L=2.20 (doble parrilla)
A46: Losa fondo — barras sentido Y (largo) | B46: #4 | C46: 0.2 | D46: 1.68 | E46: =ROUNDUP(D46/C46,0)+1 -> 10 | F46: 2 | G46: =E46*F46 -> 20 | H46: 2.6 | I46: =G46*H46 -> 52 | J46: =Supuestos!$B$5 -> 0.994 | K46: =I46*J46 -> 51.688 | L46: Corte B-B: #4 c/0.20 L=2.60 (doble parrilla)
A47: Muros sentido X — horizontales | B47: #4 | C47: 0.2 | D47: =$B$20 -> 1.2 | E47: =ROUNDUP(D47/C47,0)+1 -> 7 | F47: 2 | G47: =E47*F47 -> 14 | H47: 2.1 | I47: =G47*H47 -> 29.4 | J47: =Supuestos!$B$5 -> 0.994 | K47: =I47*J47 -> 29.2236 | L47: Planta refuerzo: #4 c/0.20 L=2.10
A48: Muros sentido Y — horizontales | B48: #4 | C48: 0.2 | D48: =$B$20 -> 1.2 | E48: =ROUNDUP(D48/C48,0)+1 -> 7 | F48: 2 | G48: =E48*F48 -> 14 | H48: 2.5 | I48: =G48*H48 -> 35 | J48: =Supuestos!$B$5 -> 0.994 | K48: =I48*J48 -> 34.79 | L48: Planta refuerzo: #4 c/0.20 L=2.50
A49: Muros sentido X — verticales (gancho a losa) | B49: #4 | C49: 0.2 | D49: =$B$11 -> 1.3 | E49: =ROUNDUP(D49/C49,0)+1 -> 8 | F49: 2 | G49: =E49*F49 -> 16 | H49: 1.75 | I49: =G49*H49 -> 28 | J49: =Supuestos!$B$5 -> 0.994 | K49: =I49*J49 -> 27.832 | L49: Cortes A-A/B-B: #4 c/0.20 L=1.75
A50: Muros sentido Y — verticales (gancho a losa) | B50: #4 | C50: 0.2 | D50: =$B$12 -> 1.7 | E50: =ROUNDUP(D50/C50,0)+1 -> 10 | F50: 2 | G50: =E50*F50 -> 20 | H50: 1.75 | I50: =G50*H50 -> 35 | J50: =Supuestos!$B$5 -> 0.994 | K50: =I50*J50 -> 34.79 | L50: Cortes A-A/B-B: #4 c/0.20 L=1.75
A51: Columnas 40×40 — longitudinal | B51: #4 | E51: 4 | F51: 4 | G51: =E51*F51 -> 16 | H51: 1.85 | I51: =G51*H51 -> 29.6 | J51: =Supuestos!$B$5 -> 0.994 | K51: =I51*J51 -> 29.4224 | L51: Confirmado: 4 #4 por columna (L=1.85 del detalle)
A52: Columnas 40×40 — flejes cerrados | B52: #3 | C52: 0.075 | D52: =$B$13 -> 1.4 | E52: =ROUNDUP(D52/C52,0)+1 -> 20 | F52: 4 | G52: =E52*F52 -> 80 | H52: 1.48 | I52: =G52*H52 -> 118.4 | J52: =Supuestos!$B$4 -> 0.56 | K52: =I52*J52 -> 66.304 | L52: Confirmado: fleje #3 @0.075 L=1.48
A53: Subtotal #4 (sin desperdicio) | I53: =SUMIF(B45:B52,"#4",I45:I52) -> 261.8 | K53: =SUMIF(B45:B52,"#4",K45:K52) -> 260.2292
A54: Subtotal #3 (sin desperdicio) | I54: =SUMIF(B45:B52,"#3",I45:I52) -> 118.4 | K54: =SUMIF(B45:B52,"#3",K45:K52) -> 66.304
A55: Cuantía de referencia (kg acero / m³ concreto) | K55: =(K53+K54)/B29 -> 120.13731
A57: E. ESTRUCTURA METÁLICA — DETALLE CONEXIÓN 1 (perfil HE 200 a columna 40×40)
A58: Elemento | B58: Cant. | C58: Und | D58: Especificación / cálculo
A59: Platina base A36 300×300×16 mm — unidades | B59: =$B$10 -> 4 | C59: un | D59: 1 por columna
A60: Platina base A36 300×300×16 mm — peso | B60: =B59*0.3*0.3*0.016*Supuestos!$B$18 -> 45.216 | C60: kg | D60: 0.30 × 0.30 × 0.016 × 7850 por platina
A61: Pernos de anclaje Ø5/8" con gancho | B61: =4*$B$10 -> 16 | C61: un | D61: 4 por platina. Longitud ≈ 0.34 m + gancho 0.10 m (detalle perno); embebido 314 mm
A62: Soldadura filete 5/16" alrededor del perfil | B62: =$B$10*1.15 -> 4.6 | C62: ml | D62: ≈1.15 m de cordón por perfil HE 200 (contorno del perfil)
A63: Perfil HE 200 — columnas del ducto (arranque) | B63: =$B$10 -> 4 | C63: un | D63: Longitud = altura del ducto hasta sala de máquinas/cubierta: NO definida en EST-02

Sheet Observaciones
A1: OBSERVACIONES, INCONSISTENCIAS Y PENDIENTES
A3: N° | B3: Tipo | C3: Observación | D3: Acción recomendada
A4: 1 | B4: Inconsistencia | C4: Área de muros: el aviso del dashboard dice 1,377.66 m² / 130 muros, pero la tabla por piso suma 1,359.15 m² / 131 muros. | D4: Se usó la tabla por piso (1,359.15 m²). Actualizar el aviso del dashboard.
A5: 2 | B5: Inconsistencia | C5: Puertas: el KPI dice 44 und, la tabla por función suma 42. En P2 la ficha del plano dice 8 puertas y la tabla 7. | D5: Re-extraer la tabla de puertas de Revit y conciliar (faltan 2 en el detalle).
A6: 3 | B6: Inconsistencia | C6: Aparatos sanitarios: el KPI dice 61, el gráfico por nivel suma 56 y la tabla detallada suma 62. | D6: Se usó la tabla detallada (62). Verificar en Revit.
A7: 4 | B7: Faltante crítico | C7: El plano estructural recibido es EST-02 de 02: falta EST-01 (cimentación general, columnas, vigas, placas, escaleras). | D7: Enviar EST-01 para cuantificar concreto y acero del edificio completo.
A8: 5 | B8: Faltante crítico | C8: El ascensor no está modelado en Revit (QA crítico). El foso aparece en EST-02 entre ejes A-B / 1-2. | D8: Coordinar la ubicación del ducto en planta arquitectónica y la ficha del proveedor (foso útil 1.20 m, luz 1.50 × 1.90 m).
A9: 6 | B9: Resuelto | C9: Columnas 40×40: confirmado 4 #4 por columna (16 barras en total). Se tomó L=1.85 m del detalle de refuerzo. | D9: Confirmado por el arquitecto. Verificar que la longitud de 1.85 m quede en la cartilla final.
A10: 7 | B10: Resuelto | C10: Flejes: confirmado fleje #3 @0.075 con L=1.48 m (80 flejes en total). | D10: Confirmado por el arquitecto.
A11: 8 | B11: EST-02 | C11: Barras de losa: la planta indica L=2.10/2.50 y los cortes L=2.20/2.60. Se usaron las de los cortes (losa) y las de planta (horizontales de muros). | D11: Confirmar la cartilla de hierros con el calculista.
A12: 9 | B12: EST-02 | C12: La lámina no indica f'c del concreto, fy del acero, recubrimientos generales ni tipo exacto de perfil (HEA/HEB 200). Se asumió 21 MPa, 420 MPa y HEB 200. | D12: Verificar en notas generales de EST-01.
A13: 10 | B13: EST-02 | C13: El rótulo indica archivo digital '2026_06_24_TANQUE ALMACENAMIENTO_T2', parece una plantilla reutilizada. | D13: Solicitar corrección del rótulo.
A14: 11 | B14: Alcance | C14: Solo se cuantifican P1–P5. P6, P7 y la cubierta siguen en diseño. | D14: Actualizar cuando se terminen esos niveles en el modelo.
A15: 12 | B15: Pendiente | C15: Sin datos para: enchapes de baños y cocinas, guardaescobas, mesones, instalaciones hidrosanitarias, eléctricas y de gas, cubierta, escaleras y barandas, aparatos de cocina. | D15: Extraer de Revit las tablas de perímetro de rooms y de acabados, y los planos técnicos.
A16: 13 | B16: Supuesto | C16: Las cantidades derivadas (unidades de mampostería, mortero, pañetes, dinteles, cielos) usan los rendimientos de la hoja Supuestos. | D16: Ajustarlos según las especificaciones definitivas del proyecto.
